fyzelogger/__init__.py
fyzelogger-0.1.1.dist-info/METADATA
fyzelogger-0.1.1.dist-info/WHEEL
fyzelogger-0.1.1.dist-info/top_level.txt
fyzelogger-0.1.1.dist-info/RECORD
