Metadata-Version: 2.4
Name: fyzelogger
Version: 0.1.1
Summary: A colorful logger with timestamp for Python
Home-page: https://github.com/FyZeAttacker/fyze-logger
Author: FyZe
Author-email: fyzejusticeeextra02@gmail.com
Classifier: Programming Language :: Python :: 3
Classifier: License :: OSI Approved :: MIT License
Classifier: Operating System :: OS Independent
Requires-Python: >=3.7
Requires-Dist: colorama
